<Plugins>
  <SubtitleEditVersion>3.3</SubtitleEditVersion>
  <Plugin>
    <Name>Dialogue one hyphen only</Name>
    <Description>Removes hyphens from second line in dialogues</Description>
    <Version>0.4</Version>
    <Date>2012-10-13</Date>
    <Url>https://github.com/SubtitleEdit/plugins/releases/download/v.1.1/DiaOneHyphen.zip</Url>
  </Plugin>
  <Plugin>
    <Name>Hearing Impaired to Uppercase</Name>
    <Description>Changes all the text inside: "[]", "()" and "{}" to Uppercase (by Ivandrofly)</Description>
    <Version>3.0</Version>
    <Date>2015-02-13</Date>
    <Url>https://github.com/SubtitleEdit/plugins/releases/download/v.1.1/HI2UC.zip</Url>
  </Plugin>
  <Plugin>
    <Name>Lines Unbreaker</Name>
    <Description>Helps breaking short lines (by Ivandrofly)</Description>
    <Version>1.1</Version>
    <Date>2014-03-09</Date>
    <Url>https://github.com/SubtitleEdit/plugins/releases/download/v.1.1/LinesUnbreaker.zip</Url>
  </Plugin>
  <Plugin>
    <Name>Load from Dropbox</Name>
    <Description>Load subtitles from Dropbox</Description>
    <Version>1.0</Version>
    <Date>2013-05-29</Date>
    <Url>http://www.nikse.dk/Content/SubtitleEdit/Plugins/SeDropBoxLoad.zip</Url>
  </Plugin>
  <Plugin>
    <Name>Save to Dropbox</Name>
    <Description>Save subtitles to Dropbox</Description>
    <Version>1.0</Version>
    <Date>2013-05-29</Date>
    <Url>https://github.com/SubtitleEdit/plugins/releases/download/v.1.1/SeDropBoxSave.zip</Url>
  </Plugin>
  <Plugin>
    <Name>Haxor</Name>
    <Description>Translates subtitle to Haxor</Description>
    <Version>1.3</Version>
    <Date>2015-02-04</Date>
    <Url>https://github.com/SubtitleEdit/plugins/releases/download/v.1.1/Haxor.zip</Url>
  </Plugin>
  <Plugin>
    <Name>Upload subtitle to OpenSubtitles.org</Name>
    <Description>Upload a subtitle quickly to OpenSubtitles.Org</Description>
    <Version>1.9</Version>
    <Date>2014-09-14</Date>
    <Url>https://github.com/SubtitleEdit/plugins/releases/download/v.1.1/OpenSubtitlesUpload.zip</Url>
  </Plugin>
  <Plugin>
    <Name>Save to Skydrive</Name>
    <Description>Upload a subtitle quickly to Skydrive</Description>
    <Version>0.2</Version>
    <Date>2013-05-29</Date>
    <Url>https://github.com/SubtitleEdit/plugins/releases/download/v.1.1/SeSkydriveSave.zip</Url>
  </Plugin>
  <Plugin>
    <Name>Load from Skydrive</Name>
    <Description>Save a subtitle quickly to Skydrive</Description>
    <Version>0.2</Version>
    <Date>2013-05-29</Date>
    <Url>https://github.com/SubtitleEdit/plugins/releases/download/v.1.1/SeSkydriveLoad.zip</Url>
  </Plugin>
  <Plugin>
    <Name>Word spell check</Name>
    <Description>Word spell check (requires Microsoft Word)</Description>
    <Version>1.1</Version>
    <Date>2014-05-25</Date>
    <Url>https://github.com/SubtitleEdit/plugins/releases/download/v.1.1/WordSpellCheck.zip</Url>
  </Plugin>
  <Plugin>
    <Name>Avi Writer</Name>
    <Description>Generate avi file with only subtitle (based on FFMPEG)</Description>
    <Version>0.4</Version>
    <Date>2015-06-24</Date>
    <Url>https://github.com/SubtitleEdit/plugins/releases/download/v.1.1/AviWriter.zip</Url>
  </Plugin>
  <Plugin>
    <Name>Dialogue AutoMarker</Name>
    <Description>Helps find and format dialogue (by Ivandrofly)</Description>
    <Version>0.1</Version>
    <Date>2014-02-04</Date>
    <Url>https://github.com/SubtitleEdit/plugins/releases/download/v.1.1/DialogueAutoMarker.zip</Url>
  </Plugin>
  <Plugin>
    <Name>Hearing Impaired Colorer</Name>
    <Description>Set color for Hearing Impaired annotations (by Ivandrofly)</Description>
    <Version>0.1</Version>
    <Date>2014-05-23</Date>
    <Url>https://github.com/SubtitleEdit/plugins/releases/download/v.1.1/HIColorer.zip</Url>
  </Plugin>
  <Plugin>
    <Name>Check Line Width</Name>
    <Description>Checks maximum line width in pixels</Description>
    <Version>0.4</Version>
    <Date>2015-05-20</Date>
    <Url>https://github.com/SubtitleEdit/plugins/releases/download/v.1.1/CheckLineWidth.zip</Url>
  </Plugin>
  <Plugin>
    <Name>American English to British English</Name>
    <Description>Convert American English to British English</Description>
    <Version>0.2</Version>
    <Date>2015-03-05</Date>
    <Url>https://github.com/SubtitleEdit/plugins/releases/download/v.1.1/AmericanToBritish.zip</Url>
  </Plugin>
</Plugins>
